ChefsHatPlayersClub/__init__.py
ChefsHatPlayersClub/agents/__init__.py
ChefsHatPlayersClub/agents/chefs_cup_v1/__init__.py
ChefsHatPlayersClub/agents/chefs_cup_v1/team_yves/__init__.py
ChefsHatPlayersClub/agents/chefs_cup_v1/team_yves/aiacimp.py
ChefsHatPlayersClub/agents/chefs_cup_v1/team_yves/ainsa.py
ChefsHatPlayersClub/agents/chefs_cup_v1/team_yves/allin.py
ChefsHatPlayersClub/agents/chefs_cup_v1/team_yves/amyg4.py
ChefsHatPlayersClub/agents/chefs_cup_v2/__init__.py
ChefsHatPlayersClub/agents/chefs_cup_v2/bloom/Bloom.py
ChefsHatPlayersClub/agents/chefs_cup_v2/bloom/__init__.py
ChefsHatPlayersClub/agents/chefs_cup_v2/larger_value/__init__.py
ChefsHatPlayersClub/agents/chefs_cup_v2/larger_value/larger_value.py
ChefsHatPlayersClub/agents/chefs_cup_v2/ppo_v2/__init__.py
ChefsHatPlayersClub/agents/chefs_cup_v2/ppo_v2/ppo_v2.py
ChefsHatPlayersClub/agents/classic/__init__.py
ChefsHatPlayersClub/agents/classic/dql.py
ChefsHatPlayersClub/agents/classic/ppo.py
ChefsHatPlayersClub/agents/karma_camaleon_club/__init__.py
ChefsHatPlayersClub/agents/karma_camaleon_club/airl.py
ChefsHatPlayersClub/agents/util/__init__.py
ChefsHatPlayersClub/agents/util/memory_buffer.py
ChefsHatPlayersClub/agents/util/sum_tree.py
ChefsHatPlayersClub-2.2.6.dist-info/LICENSE
ChefsHatPlayersClub-2.2.6.dist-info/METADATA
ChefsHatPlayersClub-2.2.6.dist-info/WHEEL
ChefsHatPlayersClub-2.2.6.dist-info/top_level.txt
ChefsHatPlayersClub-2.2.6.dist-info/RECORD
