Metadata-Version: 2.1
Name: ChefsHatPlayersClub
Version: 2.2.6
Summary: A collection of ready-to-use agents for the Chef's Hat Gym Environment
Home-page: https://github.com/pablovin/ChefsHatPlayersClub
Author: Pablo Barros
Author-email: pablovin@gmail.com
License: MIT
Classifier: Development Status :: 3 - Alpha
Classifier: Intended Audience :: Developers
Classifier: Intended Audience :: Information Technology
Classifier: Intended Audience :: Science/Research
Classifier: License :: OSI Approved :: MIT License
Classifier: Programming Language :: Python
Classifier: Programming Language :: Python :: 3.6
Classifier: Programming Language :: Python :: 3.7
Classifier: Programming Language :: Python :: 3.10
Classifier: Programming Language :: Python :: 3 :: Only
Classifier: Topic :: Games/Entertainment :: Simulation
Classifier: Topic :: Games/Entertainment :: Turn Based Strategy
Classifier: Topic :: Internet
Classifier: Topic :: Scientific/Engineering :: Artificial Intelligence
Classifier: Programming Language :: Python :: Implementation :: CPython
Classifier: Programming Language :: Python :: Implementation :: PyPy
Requires-Python: >=3.10.0
License-File: LICENSE
Requires-Dist: chefshatgym
Requires-Dist: keras ==2.14.0
Requires-Dist: numpy ==1.26.1
Requires-Dist: tensorflow ==2.14.0
